llm_rag_builder/__init__.py
llm_rag_builder/setup.py
llm_rag_builder/core/__init__.py
llm_rag_builder/core/command.py
llm_rag_builder/core/dialog.py
llm_rag_builder/core/llm.py
llm_rag_builder/core/vector_db.py
llm_rag_builder/core/vectorizer.py
llm_rag_builder/integrations/__init__.py
llm_rag_builder/integrations/chromadb/__init__.py
llm_rag_builder/integrations/chromadb/chroma_vdb.py
llm_rag_builder/integrations/gemini/__init__.py
llm_rag_builder/integrations/gemini/gemini_llm.py
llm_rag_builder/integrations/openai/__init__.py
llm_rag_builder/integrations/openai/openai_llm.py
llm_rag_builder/integrations/openai/openai_vectorizer.py
llm_rag_builder/integrations/pgvector/__init__.py
llm_rag_builder/integrations/pgvector/pgvector.py
llm_rag_builder/integrations/yandex/__init__.py
llm_rag_builder/integrations/yandex/yandex_llm.py
llm_rag_builder/integrations/yandex/yandex_vectorizer.py
llm_rag_builder/utils/__init__.py
llm_rag_builder/utils/index_md_lib.py
llm_rag_builder-0.2.9.dist-info/METADATA
llm_rag_builder-0.2.9.dist-info/WHEEL
llm_rag_builder-0.2.9.dist-info/top_level.txt
llm_rag_builder-0.2.9.dist-info/RECORD
