Metadata-Version: 2.1
Name: llm-rag-builder
Version: 0.2.9
Summary: Это библиотека на Python, предназначенная для упрощения создания и управления моделями генерации с использованием поиска (Retrieval-Augmented Generation, RAG).
Home-page: https://github.com/leo-need-more-coffee/rag_builder
Author: лень
Author-email: pzrnqt1vrss@protonmail.com
Classifier: Programming Language :: Python :: 3
Classifier: License :: OSI Approved :: MIT License
Classifier: Operating System :: OS Independent
Requires-Python: >=3.11
Provides-Extra: all
Requires-Dist: openai; extra == "all"
Requires-Dist: google-generativeai; extra == "all"
Requires-Dist: yandex-chain; extra == "all"
Requires-Dist: chromadb; extra == "all"
Requires-Dist: psycopg2; extra == "all"
Requires-Dist: pgvector; extra == "all"
Provides-Extra: chroma
Requires-Dist: chromadb; extra == "chroma"
Provides-Extra: gemini
Requires-Dist: google-generativeai; extra == "gemini"
Provides-Extra: openai
Requires-Dist: openai; extra == "openai"
Provides-Extra: pgvector
Requires-Dist: psycopg2; extra == "pgvector"
Requires-Dist: pgvector; extra == "pgvector"
Provides-Extra: yandex
Requires-Dist: yandex-chain; extra == "yandex"
